mango_test_framework/__init__.py
mango_test_framework/test_framework.py
mango_test_framework-0.1.0.dist-info/METADATA
mango_test_framework-0.1.0.dist-info/WHEEL
mango_test_framework-0.1.0.dist-info/top_level.txt
mango_test_framework-0.1.0.dist-info/RECORD
