Metadata-Version: 2.1
Name: mango-test-framework
Version: 0.1.0
Summary: A simple testing framework in Python.
Home-page: https://github.com/najasnake12/mango-test
Author: Scott
Author-email: pessiartist@gmail.com
Classifier: Development Status :: 3 - Alpha
Classifier: Intended Audience :: Developers
Classifier: License :: OSI Approved :: MIT License
Classifier: Programming Language :: Python :: 3
Classifier: Programming Language :: Python :: 3.7
Classifier: Programming Language :: Python :: 3.8
Classifier: Programming Language :: Python :: 3.9
Classifier: Programming Language :: Python :: 3.10
Classifier: Programming Language :: Python :: 3.11
Requires-Dist: mango-test-framework >=0.1.0
